nanoscipy/colors.py
nanoscipy/functions.py
nanoscipy/mathpar.py
nanoscipy/modules.py
nanoscipy/unitpar.py
nanoscipy/util.py
nanoscipy-3.0.17.dist-info/LICENSE.md
nanoscipy-3.0.17.dist-info/METADATA
nanoscipy-3.0.17.dist-info/WHEEL
nanoscipy-3.0.17.dist-info/top_level.txt
nanoscipy-3.0.17.dist-info/RECORD
