Metadata-Version: 2.1
Name: nanoscipy
Version: 3.0.17
Summary: A package containing compiled functions, to make data-handling and -analysis easier.
Home-page: https://github.com/nicholas12392/nanoscipy
Author: Nicholas Hansen
Author-email: nicholas.2000@live.dk
License: MIT
Project-URL: Bug Tracker, https://github.com/nicholas12392/nanoscipy/issues
License-File: LICENSE.md
Requires-Dist: requests
Requires-Dist: scipy
Requires-Dist: numpy
Requires-Dist: statsmodels
Requires-Dist: pandas
Requires-Dist: matplotlib
Requires-Dist: mpmath
Requires-Dist: sympy
Requires-Dist: opencv-python
